bcutils4r/__init__.py
bcutils4r/eval_classification.py
bcutils4r-0.0.24.dist-info/LICENSE
bcutils4r-0.0.24.dist-info/METADATA
bcutils4r-0.0.24.dist-info/WHEEL
bcutils4r-0.0.24.dist-info/top_level.txt
bcutils4r-0.0.24.dist-info/RECORD
