Metadata-Version: 2.1
Name: bcutils4r
Version: 0.0.24
Summary: Wrapper around some basic sklearn and scikit-plot utilities for binary classification.
Home-page: https://github.com/rutujagurav/bcutils4r
Author: Rutuja Gurav
Author-email: Rutuja Gurav <rutujagurav100@gmail.com>
Project-URL: Homepage, https://github.com/rutujagurav/bcutils4r
Project-URL: Bug Tracker, https://github.com/rutujagurav/bcutils4r/issues
Classifier: Programming Language :: Python :: 3
Classifier: License :: OSI Approved :: MIT License
Classifier: Operating System :: OS Independent
Requires-Python: >=3.6
License-File: LICENSE
Requires-Dist: deprecation
Requires-Dist: seaborn
Requires-Dist: scikit-learn
Requires-Dist: scikit-plot
